LICENSE
README.md
setup.py
BlitzOps_Python/BlitzOps.py
BlitzOps_Python/__init__.py
BlitzOps_Python.egg-info/PKG-INFO
BlitzOps_Python.egg-info/SOURCES.txt
BlitzOps_Python.egg-info/dependency_links.txt
BlitzOps_Python.egg-info/top_level.txt