Metadata-Version: 2.1
Name: BlitzOps-Python
Version: 0.0.2
Summary: Python Package for BlitzOps
Home-page: https://github.com/cvache/BlitzOps-Python
Author: Carson Vache
Author-email: carsonvache@gmail.com
License: Apache License 2.0
Classifier: Development Status :: 1 - Planning
Classifier: Programming Language :: Python :: 3.10
Classifier: Programming Language :: Python :: 3.11
License-File: LICENSE
